streamlit_sqlalchemy/__init__.py
streamlit_sqlalchemy/mixin.py
streamlit_sqlalchemy-0.2.4.dist-info/METADATA
streamlit_sqlalchemy-0.2.4.dist-info/WHEEL
streamlit_sqlalchemy-0.2.4.dist-info/licenses/LICENSE
streamlit_sqlalchemy-0.2.4.dist-info/RECORD
