Metadata-Version: 2.3
Name: streamlit-sqlalchemy
Version: 0.2.4
Summary: Some templating for streamlit and sqlalchemy
Project-URL: Homepage, https://github.com/artygo8/streamlit-sqlalchemy
Project-URL: Issues, https://github.com/artygo8/streamlit-sqlalchemy/issues
Author-email: artygo8 <arthurgossuin@gmail.com>
License-Expression: Apache-2.0
License-File: LICENSE
Keywords: database,sql,sqlalchemy,streamlit,templating
Classifier: Development Status :: 4 - Beta
Classifier: License :: OSI Approved :: Apache Software License
Classifier: Operating System :: OS Independent
Classifier: Programming Language :: Python :: 3
Requires-Python: >=3.8
Requires-Dist: sqlalchemy
Requires-Dist: streamlit>=1.29.0
